{
   "products": [
      {
         "id": 1,
         "name": "Cadeira Ergo Flex",
         "price": "99,00",
         "category": "Sala de estar",
         "description": "A Cadeira Elegância Vintage é uma peça de mobiliário que combina com maestria o charme do passado com a funcionalidade contemporânea.",
         "photoUrl": "https://source.unsplash.com/random/?chair,minimalist",
         "vendor": "Magazine Luiza"
      },
      {
         "id": 2,
         "name": "Sofá Modular Urban",
         "price": "2499,00",
         "category": "Sala de estar",
         "description": "O Sofá Modular Urban oferece estilo e versatilidade para qualquer ambiente moderno.",
         "photoUrl": "https://source.unsplash.com/random/?sofas,minimalist",
         "vendor": "Decoração Moderna"
      },
      {
         "id": 3,
         "name": "Mesa de Centro UberW",
         "price": "599,00",
         "category": "Sala de estar",
         "description": "A Mesa de Centro Minimalista é uma adição elegante a qualquer sala de estar contemporânea.",
         "photoUrl": "https://source.unsplash.com/random/?table,minimalist",
         "vendor": "Mobília Design"
      },
      {
         "id": 4,
         "name": "Estante Multiuso Wave",
         "price": "1799,00",
         "category": "Sala de estar",
         "description": "A Estante Multiuso Wave une design inovador com funcionalidade para organizar seus objetos com estilo.",
         "photoUrl": "https://source.unsplash.com/random/?bookshelf,minimalist",
         "vendor": "Inova Móveis"
      },
      {
         "id": 5,
         "name": "Cama Box Moderna",
         "price": "1199,00",
         "category": "Quarto",
         "description": "A Cama Box Moderna oferece conforto e design contemporâneo para o seu quarto.",
         "photoUrl": "https://source.unsplash.com/random/?bed,minimalist",
         "vendor": "Mobília Charmosa"
      },
      {
         "id": 6,
         "name": "Poltrona Geométrica",
         "price": "799,00",
         "category": "Sala de estar",
         "description": "A Poltrona Geométrica adiciona um toque artístico e moderno a qualquer espaço.",
         "photoUrl": "https://source.unsplash.com/random/?chair,minimalist",
         "vendor": "Estilo Único"
      },
      {
         "id": 7,
         "name": "Mesa de Jantar Sólida",
         "price": "1299,00",
         "category": "Sala de jantar",
         "description": "A Mesa de Jantar Sólida é uma peça robusta e elegante para refeições em família.",
         "photoUrl": "https://source.unsplash.com/random/?dining_table,minimalist",
         "vendor": "Decoração Sofisticada"
      },
      {
         "id": 8,
         "name": "Guarda-Roupa Espaçoso",
         "price": "1799,00",
         "category": "Quarto",
         "description": "O Guarda-Roupa Espaçoso oferece amplo espaço de armazenamento com design moderno.",
         "photoUrl": "https://source.unsplash.com/random/?wardrobe,minimalist",
         "vendor": "Móveis Funcionais"
      },
      {
         "id": 9,
         "name": "Cadeira de Escritório Ergonômica",
         "price": "399,00",
         "category": "Escritório",
         "description": "A Cadeira de Escritório Ergonômica proporciona conforto durante longas horas de trabalho.",
         "photoUrl": "https://source.unsplash.com/random/?office_chair,minimalist",
         "vendor": "Ergo Comfort"
      },
      {
         "id": 10,
         "name": "Mesa Lateral Minimalista",
         "price": "299,00",
         "category": "Sala de estar",
         "description": "A Mesa Lateral Minimalista adiciona elegância discreta a qualquer espaço.",
         "photoUrl": "https://source.unsplash.com/random/?side_table,minimalist",
         "vendor": "Mobília Simples"
      }
   ],
   "shippings": [
      {
         "id": "1",
         "name": "Correios - Normal",
         "delivery_time": "5 à 7 dias úteis",
         "price": "50"
      },
      {
         "id": "2",
         "name": "Correios - Sedex",
         "delivery_time": "5 à 7 dias úteis",
         "price": "55"
      },
      {
         "id": "3",
         "name": "Alta Azul",
         "delivery_time": "5 à 7 dias úteis",
         "price": "180"
      }
   ],
   "paymentMethods": [
      {
         "id": "1",
         "name": "Cartão de Crédito"
      }
   ],
   "users": [
      {
         "user": {
            "id": 1,
            "address": "Clemente Cunha Ferreira",
            "addressNumber": "635",
            "addressTitle": "Casa principal",
            "addressType": "Rua",
            "birthDate": "1999-06-25",
            "cellphone": "11999999999",
            "cep": "08552330",
            "city": "Poá",
            "confirmPassword": "Mat15766@",
            "country": "Brasil",
            "cpf": "99999999999",
            "description": "",
            "email": "matrodrigues1576@gmail.com",
            "fullName": "Matheus Rodrigues Bispo",
            "gender": "masculino",
            "neighborhoods": "Vila Perracini",
            "password": "Mat15766@",
            "residenceType": "Casa",
            "state": "SP"
         },
         "token": "2132178y123h1yu231y237617831e"
      }
   ]
}